wperf_cmn_visualizer/__init__.py
wperf_cmn_visualizer/__main__.py
wperf_cmn_visualizer/canvas.py
wperf_cmn_visualizer/cmn.py
wperf_cmn_visualizer/cmn_metrics.py
wperf_cmn_visualizer/config.py
wperf_cmn_visualizer/help.py
wperf_cmn_visualizer/hit_test.py
wperf_cmn_visualizer/input_dialog.py
wperf_cmn_visualizer/renderer.py
wperf_cmn_visualizer/tabbing.py
wperf_cmn_visualizer/telemetry_loader.py
wperf_cmn_visualizer/time_scrubber.py
wperf_cmn_visualizer/topology_loader.py
wperf_cmn_visualizer/wperf_cmn_visualizer.py
wperf_cmn_visualizer-1.3.0.dist-info/licenses/LICENSE
wperf_cmn_visualizer-1.3.0.dist-info/METADATA
wperf_cmn_visualizer-1.3.0.dist-info/WHEEL
wperf_cmn_visualizer-1.3.0.dist-info/entry_points.txt
wperf_cmn_visualizer-1.3.0.dist-info/top_level.txt
wperf_cmn_visualizer-1.3.0.dist-info/RECORD
