Metadata-Version: 2.4
Name: wperf-cmn-visualizer
Version: 1.3.0
Summary: A GUI-based visualizer for Arm CMN (Coherent Mesh Network) systems using WindowsPerf backend
License: BSD-3-Clause
Requires-Python: <3.14,>=3.12.4
License-File: LICENSE
Requires-Dist: PySide6
Requires-Dist: numpy
Requires-Dist: pandas
Dynamic: license-file
